finch_mlir-0.0.2.dist-info/RECORD
finch_mlir-0.0.2.dist-info/WHEEL
finch_mlir-0.0.2.dist-info/top_level.txt
finch_mlir-0.0.2.dist-info/METADATA
lib/libMLIRFinch.a
lib/libmlir_float16_utils.dylib
lib/libFinchCAPI.a
lib/libmlir_c_runner_utils.dylib
lib/libFinchCAPITestLib.dylib
lib/objects/obj.FinchCAPI/Dialects.cpp.o
mlir_finch/execution_engine.py
mlir_finch/ir.py
mlir_finch/passmanager.py
mlir_finch/rewrite.py
mlir_finch/runtime/__init__.py
mlir_finch/runtime/np_to_memref.py
mlir_finch/dialects/_memref_ops_gen.py
mlir_finch/dialects/_transform_ops_gen.py
mlir_finch/dialects/_scf_ops_gen.py
mlir_finch/dialects/_gpu_enum_gen.py
mlir_finch/dialects/_builtin_ops_gen.py
mlir_finch/dialects/finch.py
mlir_finch/dialects/_omp_ops_gen.py
mlir_finch/dialects/_nvvm_ops_gen.py
mlir_finch/dialects/_index_enum_gen.py
mlir_finch/dialects/_bufferization_ops_gen.py
mlir_finch/dialects/spirv.py
mlir_finch/dialects/_vector_ops_gen.py
mlir_finch/dialects/_bufferization_transform_ops_gen.py
mlir_finch/dialects/vector.py
mlir_finch/dialects/_async_ops_gen.py
mlir_finch/dialects/pdl.py
mlir_finch/dialects/_tosa_ops_gen.py
mlir_finch/dialects/_vector_transform_ops_gen.py
mlir_finch/dialects/cf.py
mlir_finch/dialects/rocdl.py
mlir_finch/dialects/index.py
mlir_finch/dialects/_llvm_enum_gen.py
mlir_finch/dialects/bufferization.py
mlir_finch/dialects/amdgpu.py
mlir_finch/dialects/_llvm_ops_gen.py
mlir_finch/dialects/_ml_program_ops_gen.py
mlir_finch/dialects/memref.py
mlir_finch/dialects/_complex_ops_gen.py
mlir_finch/dialects/_nvgpu_enum_gen.py
mlir_finch/dialects/_affine_enum_gen.py
mlir_finch/dialects/_pdl_ops_gen.py
mlir_finch/dialects/_rocdl_ops_gen.py
mlir_finch/dialects/_math_ops_gen.py
mlir_finch/dialects/openmp.py
mlir_finch/dialects/_ods_common.py
mlir_finch/dialects/affine.py
mlir_finch/dialects/_vector_enum_gen.py
mlir_finch/dialects/_finch_ops_gen.py
mlir_finch/dialects/_linalg_enum_gen.py
mlir_finch/dialects/nvvm.py
mlir_finch/dialects/_sparse_tensor_transform_ops_gen.py
mlir_finch/dialects/_gpu_ops_gen.py
mlir_finch/dialects/_func_ops_gen.py
