Metadata-Version: 2.1
Name: finch-mlir
Version: 0.0.2
Summary: Finch MLIR distribution as wheel.
